euxfel_bunch_pattern/__init__.py
euxfel_bunch_pattern/_version.py
euxfel_bunch_pattern/tests/__init__.py
euxfel_bunch_pattern/tests/test_bunch_pattern.py
euxfel_bunch_pattern-0.6.dist-info/LICENSE
euxfel_bunch_pattern-0.6.dist-info/METADATA
euxfel_bunch_pattern-0.6.dist-info/WHEEL
euxfel_bunch_pattern-0.6.dist-info/top_level.txt
euxfel_bunch_pattern-0.6.dist-info/RECORD
