Metadata-Version: 2.1
Name: euxfel-bunch-pattern
Version: 0.6
Summary: Decoding EuXFEL bunch pattern tables
Home-page: https://git.xfel.eu/gitlab/karaboDevices/euxfel_bunch_pattern
Author: UNKNOWN
Author-email: UNKNOWN
License: UNKNOWN
Platform: UNKNOWN
Requires-Dist: numpy
